awsssocredrestore/__init__.py
aws_sso_cred_restore-1.0.0.dist-info/LICENSE
aws_sso_cred_restore-1.0.0.dist-info/METADATA
aws_sso_cred_restore-1.0.0.dist-info/WHEEL
aws_sso_cred_restore-1.0.0.dist-info/entry_points.txt
aws_sso_cred_restore-1.0.0.dist-info/top_level.txt
aws_sso_cred_restore-1.0.0.dist-info/RECORD
