Metadata-Version: 2.1
Name: aws-sso-cred-restore
Version: 1.0.0
Summary: A wrapper for executing a command with AWS CLI v2 and SSO, inspired from aws2-wrap
Home-page: https://github.com/claytonsilva/aws-sso-cred-restore
Author: Clayton Silva
Author-email: clayton.silva@pagar.me
License: GNU General Public License v3 (GPLv3)
Keywords: aws profile sso assume role
Platform: UNKNOWN
Classifier: Development Status :: 3 - Alpha
Classifier: Intended Audience :: Developers
Classifier: Programming Language :: Python :: 3
Classifier: Environment :: Console
Classifier: License :: OSI Approved :: GNU General Public License v3 (GPLv3)
Classifier: Operating System :: OS Independent
Requires-Python: >=3.6
